pybemolle/__init__.py
pybemolle/filters.py
pybemolle/formatters.py
pybemolle/lexers.py
pybemolle/styles.py
pybemolle/tokens.py
pybemolle-0.0.2.dist-info/AUTHORS
pybemolle-0.0.2.dist-info/LICENSE
pybemolle-0.0.2.dist-info/METADATA
pybemolle-0.0.2.dist-info/WHEEL
pybemolle-0.0.2.dist-info/entry_points.txt
pybemolle-0.0.2.dist-info/top_level.txt
pybemolle-0.0.2.dist-info/RECORD
