Metadata-Version: 2.1
Name: pybemolle
Version: 0.0.2
Summary: 
Requires-Dist: pygments (>=2.4.2)
Provides-Extra: dev
Requires-Dist: setuptools ; extra == 'dev'
Requires-Dist: twine ; extra == 'dev'
Requires-Dist: pytest ; extra == 'dev'
Requires-Dist: pytest-pep8 ; extra == 'dev'
Requires-Dist: pytest-cov ; extra == 'dev'
Requires-Dist: python-coveralls ; extra == 'dev'
